{"modules":[{"name":"managerial_accounting","id":"acc_man_560","ects":8,"workloadInPerson":24,"workloadSelfStudy":216,"offeredIn":[],"recommendedSemester":[],"recommendedLiterature":["None provided"],"hasLecturer":[{"name":"Jannis Bischof","title":"Prof. Dr.","hasName":true},{"name":"Claudia Max","title":"Dr.","hasName":true},{"name":"Can Toygar","title":null,"hasName":false}],"hasPersonInCharge":[{"name":"Jannis Bischof","title":"Prof. Dr.","hasName":true}],"assessmentForms":["WRITTEN","PRESENTATION"],"examinationDistribution":"25/75","examinationDuration":90,"requiredPrerequisiteModules":[],"optionalPrerequisiteModules":["Bachelor-level knowledge of cost accounting"],"additionalPrerequisite":null,"furtherModules":["None provided"]},{"name":"science_management","id":"man_521","ects":4,"workloadInPerson":11,"workloadSelfStudy":109,"offeredIn":[],"recommendedSemester":[],"recommendedLiterature":["None provided"],"hasLecturer":[{"name":"Yvonne Dorf","title":"Dr.","hasName":true}],"hasPersonInCharge":[{"name":"Yvonne Dorf","title":"Dr.","hasName":true}],"assessmentForms":["WRITTEN"],"examinationDistribution":"100","examinationDuration":60,"requiredPrerequisiteModules":[],"optionalPrerequisiteModules":[],"additionalPrerequisite":"Interest in gaining comprehensive knowledge in various disciplines of science management.","furtherModules":["None provided"]},{"name":"responsibility_in_management","id":"man_522","ects":4,"workloadInPerson":10,"workloadSelfStudy":110,"offeredIn":[],"recommendedSemester":[],"recommendedLiterature":["None provided"],"hasLecturer":[{"name":"Carsten Lotz","title":"Dr.","hasName":true}],"hasPersonInCharge":[{"name":"Carsten Lotz","title":"Dr.","hasName":true}],"assessmentForms":["WRITTEN"],"examinationDistribution":"100","examinationDuration":60,"requiredPrerequisiteModules":[],"optionalPrerequisiteModules":["Acquisition of the philosophical and economic literature mentioned in the lecture."],"additionalPrerequisite":null,"furtherModules":["None provided"]},{"name":"international_course_management","id":"man_550","ects":0,"workloadInPerson":0,"workloadSelfStudy":0,"offeredIn":[],"recommendedSemester":[],"recommendedLiterature":["Depends on course taken abroad"],"hasLecturer":[{"name":"Lecturer at the host university.","title":null,"hasName":false}],"hasPersonInCharge":[{"name":"Lecturer at the host university.","title":null,"hasName":false}],"assessmentForms":[],"examinationDistribution":null,"examinationDuration":null,"requiredPrerequisiteModules":["Level of the course matches that of regular MMM course (level 500 and above)"],"optionalPrerequisiteModules":[],"additionalPrerequisite":null,"furtherModules":["None provided"]},{"name":"corporate_sustainability","id":"acc_man_660","ects":4,"workloadInPerson":11,"workloadSelfStudy":109,"offeredIn":[],"recommendedSemester":[],"recommendedLiterature":["None provided"],"hasLecturer":[{"name":"Holger Rubel","title":"Dr.","hasName":true}],"hasPersonInCharge":[{"name":"Jannis Bischof","title":"Prof. Dr.","hasName":true}],"assessmentForms":["WRITTEN"],"examinationDistribution":"100","examinationDuration":60,"requiredPrerequisiteModules":[],"optionalPrerequisiteModules":["Bachelor-level knowledge of value-based management"],"additionalPrerequisite":null,"furtherModules":["None provided"]},{"name":"corporate_sustainability_performance","id":"acc_man_661","ects":6,"workloadInPerson":16,"workloadSelfStudy":164,"offeredIn":[],"recommendedSemester":[],"recommendedLiterature":["None provided"],"hasLecturer":[{"name":"Holger Rubel","title":"Dr.","hasName":true}],"hasPersonInCharge":[{"name":"Jannis Bischof","title":"Prof. Dr.","hasName":true}],"assessmentForms":["WRITTEN","PRESENTATION"],"examinationDistribution":"25/75","examinationDuration":45,"requiredPrerequisiteModules":["ACC 510","ACC 520","ACC 530","ACC 540","ACC 560","ACC/TAX 570"],"optionalPrerequisiteModules":["ACC 660","Bachelor-level knowledge of sustainability management and performance measurement"],"additionalPrerequisite":null,"furtherModules":["None provided"]},{"name":"private_equity_due_diligence","id":"acc_man_662","ects":6,"workloadInPerson":16,"workloadSelfStudy":164,"offeredIn":[],"recommendedSemester":[],"recommendedLiterature":["None provided"],"hasLecturer":[{"name":"Wilhelm Schmundt","title":"Prof. Dr.","hasName":true}],"hasPersonInCharge":[{"name":"Wilhelm Schmundt","title":"Prof. Dr.","hasName":true}],"assessmentForms":["WRITTEN","PRESENTATION"],"examinationDistribution":"50/50","examinationDuration":45,"requiredPrerequisiteModules":["ACC 510","ACC 520","ACC 530","ACC 540","ACC 560","ACC/TAX 570"],"optionalPrerequisiteModules":["Basic knowledge of Corporate Finance"],"additionalPrerequisite":null,"furtherModules":["None provided"]},{"name":"business_society_environment","id":"man_608","ects":4,"workloadInPerson":11,"workloadSelfStudy":109,"offeredIn":[],"recommendedSemester":[],"recommendedLiterature":["None provided"],"hasLecturer":[{"name":"Karin Hoisl","title":"Prof. Dr.","hasName":true}],"hasPersonInCharge":[{"name":"Karin Hoisl","title":"Prof. Dr.","hasName":true}],"assessmentForms":["PRESENTATION","WRITTEN"],"examinationDistribution":"30/70","examinationDuration":60,"requiredPrerequisiteModules":[],"optionalPrerequisiteModules":[],"additionalPrerequisite":null,"furtherModules":["None provided"]},{"name":"strategic_management_between_profit_and_purpose","id":"man_609","ects":4,"workloadInPerson":11,"workloadSelfStudy":109,"offeredIn":[],"recommendedSemester":[],"recommendedLiterature":["None provided"],"hasLecturer":[{"name":"Moritz Motyka","title":"Dr.","hasName":true}],"hasPersonInCharge":[{"name":"Moritz Motyka","title":"Dr.","hasName":true}],"assessmentForms":["PRESENTATION","WRITTEN"],"examinationDistribution":"50/50","examinationDuration":60,"requiredPrerequisiteModules":[],"optionalPrerequisiteModules":["Completion of the introductory course MAN 679"],"additionalPrerequisite":null,"furtherModules":["None provided"]},{"name":"entrepreneurship_innovation","id":"man_626","ects":3,"workloadInPerson":6,"workloadSelfStudy":84,"offeredIn":[],"recommendedSemester":[],"recommendedLiterature":["None provided"],"hasLecturer":[{"name":"Jan-Philipp Ahrens","title":"PD Dr. habil.","hasName":true}],"hasPersonInCharge":[{"name":"Jan-Philipp Ahrens","title":"PD Dr. habil.","hasName":true}],"assessmentForms":["PRESENTATION"],"examinationDistribution":"75/12.5/12.5","examinationDuration":null,"requiredPrerequisiteModules":[],"optionalPrerequisiteModules":[],"additionalPrerequisite":null,"furtherModules":["None provided"]},{"name":"introduction_to_entrepreneurship","id":"man_630","ects":6,"workloadInPerson":12,"workloadSelfStudy":168,"offeredIn":[],"recommendedSemester":[],"recommendedLiterature":["None provided"],"hasLecturer":[{"name":"Michael Woywode","title":"Prof. Dr.","hasName":true}],"hasPersonInCharge":[{"name":"Michael Woywode","title":"Prof. Dr.","hasName":true}],"assessmentForms":["WRITTEN","PRESENTATION"],"examinationDistribution":"50/40/10","examinationDuration":60,"requiredPrerequisiteModules":[],"optionalPrerequisiteModules":[],"additionalPrerequisite":null,"furtherModules":["None provided"]},{"name":"creativity_and_entrepreneurship_in_practice","id":"man_631","ects":6,"workloadInPerson":12,"workloadSelfStudy":168,"offeredIn":[],"recommendedSemester":[],"recommendedLiterature":["None provided"],"hasLecturer":[{"name":"Michael Woywode","title":"Prof. Dr.","hasName":true},{"name":"Nora Zybura","title":null,"hasName":false},{"name":"Bettina Müller","title":"Dr.","hasName":true}],"hasPersonInCharge":[{"name":"Michael Woywode","title":"Prof. Dr.","hasName":true}],"assessmentForms":["PRESENTATION","REPORT","WRITTEN"],"examinationDistribution":"35/35/20/10","examinationDuration":null,"requiredPrerequisiteModules":[],"optionalPrerequisiteModules":["MAN 630 or MAN 632"],"additionalPrerequisite":null,"furtherModules":["None provided"]},{"name":"advanced_entrepreneurship","id":"man_632","ects":6,"workloadInPerson":12,"workloadSelfStudy":168,"offeredIn":[],"recommendedSemester":[],"recommendedLiterature":["None provided"],"hasLecturer":[{"name":"Michael Woywode","title":"Prof. Dr.","hasName":true}],"hasPersonInCharge":[{"name":"Michael Woywode","title":"Prof. Dr.","hasName":true}],"assessmentForms":["PRESENTATION","WRITTEN"],"examinationDistribution":"50/40/10","examinationDuration":60,"requiredPrerequisiteModules":[],"optionalPrerequisiteModules":["MAN 630 or MAN 632"],"additionalPrerequisite":null,"furtherModules":["None provided"]},{"name":"entrepreneurial_behavior_and_crowdfunding_social_ventures","id":"man_634","ects":6,"workloadInPerson":12,"workloadSelfStudy":168,"offeredIn":[],"recommendedSemester":[],"recommendedLiterature":["None provided"],"hasLecturer":[{"name":"Baris Istipliler","title":"Dr.","hasName":true}],"hasPersonInCharge":[{"name":"Baris Istipliler","title":"Dr.","hasName":true}],"assessmentForms":["PRESENTATION","REPORT","WRITTEN"],"examinationDistribution":"40/35/25","examinationDuration":null,"requiredPrerequisiteModules":["MAN 626"],"optionalPrerequisiteModules":[],"additionalPrerequisite":null,"furtherModules":["None provided"]},{"name":"employment_relations","id":"man_638","ects":4,"workloadInPerson":10,"workloadSelfStudy":110,"offeredIn":[],"recommendedSemester":[],"recommendedLiterature":["None provided"],"hasLecturer":[{"name":"Frank Danesy","title":"Dr.","hasName":true}],"hasPersonInCharge":[{"name":"Frank Danesy","title":"Dr.","hasName":true}],"assessmentForms":["WRITTEN"],"examinationDistribution":null,"examinationDuration":60,"requiredPrerequisiteModules":[],"optionalPrerequisiteModules":[],"additionalPrerequisite":null,"furtherModules":["None provided"]},{"name":"transform_innovation_entrepreneurship_for_sustainability","id":"man_639","ects":0,"workloadInPerson":0,"workloadSelfStudy":0,"offeredIn":[],"recommendedSemester":[],"recommendedLiterature":["None provided"],"hasLecturer":[{"name":"Various","title":null,"hasName":false}],"hasPersonInCharge":[{"name":"Various","title":null,"hasName":false}],"assessmentForms":[],"examinationDistribution":null,"examinationDuration":null,"requiredPrerequisiteModules":[],"optionalPrerequisiteModules":[],"additionalPrerequisite":null,"furtherModules":["None provided"]},{"name":"human_resource_training_development","id":"man_644","ects":6,"workloadInPerson":14,"workloadSelfStudy":166,"offeredIn":[],"recommendedSemester":[],"recommendedLiterature":["None provided"],"hasLecturer":[{"name":"Frank Danesy","title":"Dr.","hasName":true}],"hasPersonInCharge":[{"name":"Frank Danesy","title":"Dr.","hasName":true}],"assessmentForms":["WRITTEN"],"examinationDistribution":"75/25","examinationDuration":60,"requiredPrerequisiteModules":[],"optionalPrerequisiteModules":[],"additionalPrerequisite":null,"furtherModules":["None provided"]},{"name":"leadership_motivation","id":"man_645","ects":6,"workloadInPerson":14,"workloadSelfStudy":166,"offeredIn":[],"recommendedSemester":[],"recommendedLiterature":["None provided"],"hasLecturer":[{"name":"Torsten Biemann","title":"Prof. Dr.","hasName":true}],"hasPersonInCharge":[{"name":"Torsten Biemann","title":"Prof. Dr.","hasName":true}],"assessmentForms":["WRITTEN"],"examinationDistribution":"100","examinationDuration":60,"requiredPrerequisiteModules":[],"optionalPrerequisiteModules":[],"additionalPrerequisite":null,"furtherModules":["None provided"]},{"name":"hr_analytics","id":"man_646","ects":6,"workloadInPerson":14,"workloadSelfStudy":166,"offeredIn":[],"recommendedSemester":[],"recommendedLiterature":["None provided"],"hasLecturer":[{"name":"Torsten Biemann","title":"Prof. Dr.","hasName":true}],"hasPersonInCharge":[{"name":"Torsten Biemann","title":"Prof. Dr.","hasName":true}],"assessmentForms":["WRITTEN"],"examinationDistribution":"100","examinationDuration":60,"requiredPrerequisiteModules":[],"optionalPrerequisiteModules":["Module MAN 645 or MAN 647"],"additionalPrerequisite":null,"furtherModules":["None provided"]},{"name":"strategic_international_hr_management","id":"man_647","ects":6,"workloadInPerson":14,"workloadSelfStudy":166,"offeredIn":[],"recommendedSemester":[],"recommendedLiterature":["None provided"],"hasLecturer":[{"name":"Torsten Biemann","title":"Prof. Dr.","hasName":true}],"hasPersonInCharge":[{"name":"Torsten Biemann","title":"Prof. Dr.","hasName":true}],"assessmentForms":["WRITTEN"],"examinationDistribution":"100","examinationDuration":60,"requiredPrerequisiteModules":[],"optionalPrerequisiteModules":[],"additionalPrerequisite":null,"furtherModules":["None provided"]},{"name":"incentives_performance","id":"man_648","ects":6,"workloadInPerson":14,"workloadSelfStudy":166,"offeredIn":[],"recommendedSemester":[],"recommendedLiterature":["None provided"],"hasLecturer":[{"name":"Torsten Biemann","title":"Prof. Dr.","hasName":true}],"hasPersonInCharge":[{"name":"Torsten Biemann","title":"Prof. Dr.","hasName":true}],"assessmentForms":["WRITTEN"],"examinationDistribution":"100","examinationDuration":60,"requiredPrerequisiteModules":["MAN 645 or MAN 647"],"optionalPrerequisiteModules":[],"additionalPrerequisite":null,"furtherModules":["None provided"]},{"name":"hr_recruitment_selection","id":"man_649","ects":6,"workloadInPerson":14,"workloadSelfStudy":166,"offeredIn":[],"recommendedSemester":[],"recommendedLiterature":["None provided"],"hasLecturer":[{"name":"Frank Danesy","title":"Dr.","hasName":true}],"hasPersonInCharge":[{"name":"Frank Danesy","title":"Dr.","hasName":true}],"assessmentForms":["WRITTEN"],"examinationDistribution":"75/25","examinationDuration":60,"requiredPrerequisiteModules":[],"optionalPrerequisiteModules":[],"additionalPrerequisite":null,"furtherModules":["None provided"]},{"name":"corporate_restructuring","id":"man_654","ects":6,"workloadInPerson":16,"workloadSelfStudy":164,"offeredIn":[],"recommendedSemester":[],"recommendedLiterature":["None provided"],"hasLecturer":[{"name":"Matthias Brauer","title":"Prof. Dr.","hasName":true}],"hasPersonInCharge":[{"name":"Matthias Brauer","title":"Prof. Dr.","hasName":true}],"assessmentForms":["WRITTEN","PRESENTATION"],"examinationDistribution":null,"examinationDuration":60,"requiredPrerequisiteModules":["Not taken MAN 656"],"optionalPrerequisiteModules":[],"additionalPrerequisite":null,"furtherModules":["None provided"]},{"name":"corporate_strategy","id":"man_655","ects":4,"workloadInPerson":12,"workloadSelfStudy":108,"offeredIn":[],"recommendedSemester":[],"recommendedLiterature":["None provided"],"hasLecturer":[{"name":"Matthias Brauer","title":"Prof. Dr.","hasName":true}],"hasPersonInCharge":[{"name":"Matthias Brauer","title":"Prof. Dr.","hasName":true}],"assessmentForms":["WRITTEN"],"examinationDistribution":null,"examinationDuration":60,"requiredPrerequisiteModules":[],"optionalPrerequisiteModules":["Knowledge in strategic management"],"additionalPrerequisite":null,"furtherModules":["None provided"]},{"name":"mergers_acquisitions","id":"man_656","ects":6,"workloadInPerson":16,"workloadSelfStudy":164,"offeredIn":[],"recommendedSemester":[],"recommendedLiterature":["None provided"],"hasLecturer":[{"name":"Matthias Brauer","title":"Prof. Dr.","hasName":true}],"hasPersonInCharge":[{"name":"Matthias Brauer","title":"Prof. Dr.","hasName":true}],"assessmentForms":["WRITTEN","PRESENTATION"],"examinationDistribution":null,"examinationDuration":60,"requiredPrerequisiteModules":["Not taken MAN 654"],"optionalPrerequisiteModules":[],"additionalPrerequisite":null,"furtherModules":["None provided"]},{"name":"understanding_societal_challenges_management_research","id":"man_659","ects":6,"workloadInPerson":12,"workloadSelfStudy":168,"offeredIn":[],"recommendedSemester":[],"recommendedLiterature":["None provided"],"hasLecturer":[{"name":"Bernd Helmig","title":"Prof. Dr.","hasName":true}],"hasPersonInCharge":[{"name":"Bernd Helmig","title":"Prof. Dr.","hasName":true}],"assessmentForms":["PRESENTATION"],"examinationDistribution":null,"examinationDuration":null,"requiredPrerequisiteModules":[],"optionalPrerequisiteModules":[],"additionalPrerequisite":null,"furtherModules":["None provided"]},{"name":"sustainability_management_simulation","id":"man_665","ects":2,"workloadInPerson":6,"workloadSelfStudy":54,"offeredIn":[],"recommendedSemester":[],"recommendedLiterature":["None provided"],"hasLecturer":[{"name":"Florian Stahl","title":"Prof. Dr.","hasName":true}],"hasPersonInCharge":[{"name":"Florian Stahl","title":"Prof. Dr.","hasName":true}],"assessmentForms":["PRESENTATION","REPORT"],"examinationDistribution":"50/25/25","examinationDuration":null,"requiredPrerequisiteModules":[],"optionalPrerequisiteModules":[],"additionalPrerequisite":null,"furtherModules":["None provided"]},{"name":"leadership_in_organizations","id":"man_668","ects":4,"workloadInPerson":6,"workloadSelfStudy":114,"offeredIn":[],"recommendedSemester":[],"recommendedLiterature":["None provided"],"hasLecturer":[{"name":"Peter Finzer","title":"Prof. Dr.","hasName":true}],"hasPersonInCharge":[{"name":"Peter Finzer","title":"Prof. Dr.","hasName":true}],"assessmentForms":["WRITTEN","PRESENTATION"],"examinationDistribution":null,"examinationDuration":null,"requiredPrerequisiteModules":[],"optionalPrerequisiteModules":[],"additionalPrerequisite":null,"furtherModules":["None provided"]},{"name":"selected_challenges_in_nonprofit_management","id":"man_675","ects":6,"workloadInPerson":14,"workloadSelfStudy":166,"offeredIn":[],"recommendedSemester":[],"recommendedLiterature":["Helmig, B. & Boenigk, S. (2020). Nonprofit Management. 2nd edition, München: Vahlen."],"hasLecturer":[{"name":"Bernd Helmig","title":"Prof. Dr.","hasName":true}],"hasPersonInCharge":[{"name":"Bernd Helmig","title":"Prof. Dr.","hasName":true}],"assessmentForms":["PRESENTATION","WRITTEN"],"examinationDistribution":"25/75","examinationDuration":null,"requiredPrerequisiteModules":[],"optionalPrerequisiteModules":[],"additionalPrerequisite":null,"furtherModules":["None provided"]},{"name":"selected_challenges_in_public_management","id":"man_676","ects":6,"workloadInPerson":14,"workloadSelfStudy":166,"offeredIn":[],"recommendedSemester":[],"recommendedLiterature":["None provided"],"hasLecturer":[{"name":"Bernd Helmig","title":"Prof. Dr.","hasName":true}],"hasPersonInCharge":[{"name":"Bernd Helmig","title":"Prof. Dr.","hasName":true}],"assessmentForms":["PRESENTATION","WRITTEN"],"examinationDistribution":"30/70","examinationDuration":null,"requiredPrerequisiteModules":[],"optionalPrerequisiteModules":[],"additionalPrerequisite":null,"furtherModules":["None provided"]},{"name":"scientific_introduction_into_public_and_noprofit_management","id":"man_679","ects":6,"workloadInPerson":12,"workloadSelfStudy":168,"offeredIn":[],"recommendedSemester":[],"recommendedLiterature":["None provided"],"hasLecturer":[{"name":"Bernd Helmig","title":"Prof. Dr.","hasName":true}],"hasPersonInCharge":[{"name":"Bernd Helmig","title":"Prof. Dr.","hasName":true}],"assessmentForms":["WRITTEN","PRESENTATION"],"examinationDistribution":"90/10","examinationDuration":90,"requiredPrerequisiteModules":[],"optionalPrerequisiteModules":[],"additionalPrerequisite":null,"furtherModules":["None provided"]},{"name":"challenges_of_public_and_nonprofit_management","id":"man_680","ects":6,"workloadInPerson":12,"workloadSelfStudy":168,"offeredIn":[],"recommendedSemester":[],"recommendedLiterature":["None provided"],"hasLecturer":[{"name":"Bernd Helmig","title":"Prof. Dr.","hasName":true}],"hasPersonInCharge":[{"name":"Bernd Helmig","title":"Prof. Dr.","hasName":true}],"assessmentForms":["PRESENTATION","WRITTEN"],"examinationDistribution":"40/60","examinationDuration":null,"requiredPrerequisiteModules":[],"optionalPrerequisiteModules":[],"additionalPrerequisite":null,"furtherModules":["None provided"]},{"name":"innovation_management","id":"man_690","ects":4,"workloadInPerson":12,"workloadSelfStudy":108,"offeredIn":[],"recommendedSemester":[],"recommendedLiterature":["None provided"],"hasLecturer":[{"name":"Karin Hoisl","title":"Prof. Dr.","hasName":true}],"hasPersonInCharge":[{"name":"Karin Hoisl","title":"Prof. Dr.","hasName":true}],"assessmentForms":["WRITTEN"],"examinationDistribution":null,"examinationDuration":60,"requiredPrerequisiteModules":[],"optionalPrerequisiteModules":["Basic bachelor-level knowledge on organization and management"],"additionalPrerequisite":null,"furtherModules":["None provided"]},{"name":"selected_topics_in_organizational_behavior","id":"man_691","ects":4,"workloadInPerson":12,"workloadSelfStudy":108,"offeredIn":[],"recommendedSemester":[],"recommendedLiterature":["None provided"],"hasLecturer":[{"name":"Karin Hoisl","title":"Prof. Dr.","hasName":true}],"hasPersonInCharge":[{"name":"Karin Hoisl","title":"Prof. Dr.","hasName":true}],"assessmentForms":["WRITTEN"],"examinationDistribution":null,"examinationDuration":60,"requiredPrerequisiteModules":[],"optionalPrerequisiteModules":["Basic bachelor-level knowledge on organization and management"],"additionalPrerequisite":null,"furtherModules":["None provided"]},{"name":"strategic_intellectual_property_management","id":"man_693","ects":4,"workloadInPerson":12,"workloadSelfStudy":108,"offeredIn":[],"recommendedSemester":[],"recommendedLiterature":["None provided"],"hasLecturer":[{"name":"Karin Hoisl","title":"Prof. Dr.","hasName":true}],"hasPersonInCharge":[{"name":"Karin Hoisl","title":"Prof. Dr.","hasName":true}],"assessmentForms":["WRITTEN"],"examinationDistribution":null,"examinationDuration":60,"requiredPrerequisiteModules":[],"optionalPrerequisiteModules":["Basic bachelor-level knowledge on organization and management"],"additionalPrerequisite":null,"furtherModules":["None provided"]},{"name":"advanced_topics_in_digital_transformation","id":"man_699","ects":6,"workloadInPerson":30,"workloadSelfStudy":150,"offeredIn":[],"recommendedSemester":[],"recommendedLiterature":["None provided"],"hasLecturer":[{"name":"Karin Hoisl","title":"Prof. Dr.","hasName":true}],"hasPersonInCharge":[{"name":"Karin Hoisl","title":"Prof. Dr.","hasName":true}],"assessmentForms":["PRESENTATION"],"examinationDistribution":null,"examinationDuration":null,"requiredPrerequisiteModules":[],"optionalPrerequisiteModules":["Master-level knowledge on innovation and management"],"additionalPrerequisite":null,"furtherModules":["None provided"]},{"name":"research_seminar_public_nonprofit_management","id":"man_710","ects":6,"workloadInPerson":45,"workloadSelfStudy":135,"offeredIn":[],"recommendedSemester":[],"recommendedLiterature":["None provided"],"hasLecturer":[{"name":"Bernd Helmig","title":"Prof. Dr.","hasName":true}],"hasPersonInCharge":[{"name":"Bernd Helmig","title":"Prof. Dr.","hasName":true}],"assessmentForms":["WRITTEN"],"examinationDistribution":"25/75","examinationDuration":null,"requiredPrerequisiteModules":["MAN 609, MAN 659, MAN 675, MAN 676, MAN 679, MAN 680"],"optionalPrerequisiteModules":[],"additionalPrerequisite":null,"furtherModules":["None provided"]},{"name":"research_seminar_organization_innovation","id":"man_721","ects":6,"workloadInPerson":45,"workloadSelfStudy":135,"offeredIn":[],"recommendedSemester":[],"recommendedLiterature":["None provided"],"hasLecturer":[{"name":"Karin Hoisl","title":"Prof. Dr.","hasName":true}],"hasPersonInCharge":[{"name":"Karin Hoisl","title":"Prof. Dr.","hasName":true}],"assessmentForms":["WRITTEN"],"examinationDistribution":null,"examinationDuration":null,"requiredPrerequisiteModules":[],"optionalPrerequisiteModules":["MAN 690, MAN 691, MAN 693"],"additionalPrerequisite":null,"furtherModules":["None provided"]},{"name":"research_seminar_human_resource_management_leadership","id":"man_741","ects":6,"workloadInPerson":45,"workloadSelfStudy":135,"offeredIn":[],"recommendedSemester":[],"recommendedLiterature":["None provided"],"hasLecturer":[{"name":"Torsten Biemann","title":"Prof. Dr.","hasName":true}],"hasPersonInCharge":[{"name":"Torsten Biemann","title":"Prof. Dr.","hasName":true}],"assessmentForms":["WRITTEN","PRESENTATION"],"examinationDistribution":"30/70","examinationDuration":null,"requiredPrerequisiteModules":["At least one master level course attended at the chair (MAN 64X)"],"optionalPrerequisiteModules":[],"additionalPrerequisite":null,"furtherModules":["None provided"]},{"name":"seminar_corporate_strategy_governance","id":"man_750","ects":6,"workloadInPerson":45,"workloadSelfStudy":135,"offeredIn":[],"recommendedSemester":[],"recommendedLiterature":["None provided"],"hasLecturer":[{"name":"Matthias Brauer","title":"Prof. Dr.","hasName":true}],"hasPersonInCharge":[{"name":"Matthias Brauer","title":"Prof. Dr.","hasName":true}],"assessmentForms":["WRITTEN"],"examinationDistribution":"66.6/33.3","examinationDuration":null,"requiredPrerequisiteModules":["MAN 654 or MAN 655 or MAN 656"],"optionalPrerequisiteModules":[],"additionalPrerequisite":null,"furtherModules":["None provided"]},{"name":"research_seminar_family_business_entrepreneurship","id":"man_770","ects":6,"workloadInPerson":45,"workloadSelfStudy":135,"offeredIn":[],"recommendedSemester":[],"recommendedLiterature":["None provided"],"hasLecturer":[{"name":"Karin Hoisl","title":"Prof. Dr.","hasName":true}],"hasPersonInCharge":[{"name":"Karin Hoisl","title":"Prof. Dr.","hasName":true}],"assessmentForms":["WRITTEN"],"examinationDistribution":"33.3/33.3/33.3","examinationDuration":null,"requiredPrerequisiteModules":[],"optionalPrerequisiteModules":[],"additionalPrerequisite":null,"furtherModules":["None provided"]},{"name":"corporate_decarbonization","id":"man_771","ects":6,"workloadInPerson":45,"workloadSelfStudy":135,"offeredIn":[],"recommendedSemester":[],"recommendedLiterature":["None provided"],"hasLecturer":[{"name":"Gunther Glenk","title":"Prof. Dr.","hasName":true},{"name":"Stefan Reichelstein","title":"Prof. Dr.","hasName":true},{"name":"Amadeus Bach","title":null,"hasName":false}],"hasPersonInCharge":[{"name":"Gunther Glenk","title":"Prof. Dr.","hasName":true}],"assessmentForms":["WRITTEN","PRESENTATION"],"examinationDistribution":"70/30","examinationDuration":null,"requiredPrerequisiteModules":[],"optionalPrerequisiteModules":["Basic knowledge of econometrics and statistical methods"],"additionalPrerequisite":null,"furtherModules":["None provided"]}]}